kitsec/__init__.py
kitsec/cli/__init__.py
kitsec/cli/cve.py
kitsec/cli/dependencies.py
kitsec/cli/enumerator.py
kitsec/cli/fuzz.py
kitsec/cli/main.py
kitsec/cli/network.py
kitsec/cli/utils.py
kitsec/lists/fuzz/file_fuzz/file_fuzz.txt
kitsec/lists/fuzz/path_fuzz/asp.txt
kitsec/lists/fuzz/path_fuzz/aspx.txt
kitsec/lists/fuzz/path_fuzz/cfm.txt
kitsec/lists/fuzz/path_fuzz/cgi.txt
kitsec/lists/fuzz/path_fuzz/cve.txt
kitsec/lists/fuzz/path_fuzz/default.txt
kitsec/lists/fuzz/path_fuzz/jsp.txt
kitsec/lists/fuzz/path_fuzz/leaky-paths.txt
kitsec/lists/fuzz/path_fuzz/msfPaths.txt
kitsec/lists/fuzz/path_fuzz/others.txt
kitsec/lists/fuzz/path_fuzz/packetstormPaths.txt
kitsec/lists/fuzz/path_fuzz/perl.txt
kitsec/lists/fuzz/path_fuzz/php.txt
kitsec/lists/fuzz/path_fuzz/swagger-wordlist.txt
kitsec/lists/fuzz/path_fuzz/webapps.txt
kitsec/lists/fuzz/path_fuzz/z_all.txt
kitsec/lists/passwords/1000000-password-seclists.txt
kitsec/lists/passwords/2151220-passwords.txt
kitsec/lists/passwords/38650-password-sktorrent.txt
kitsec/lists/passwords/38650-username-sktorrent.txt
kitsec/lists/passwords/7-more-passwords.txt
kitsec/lists/passwords/8-more-passwords.txt
kitsec/lists/passwords/cain.txt
kitsec/lists/passwords/facebook-firstnames.txt
kitsec/lists/passwords/indo-cities.txt
kitsec/lists/passwords/subdomains-10000.txt
kitsec/lists/passwords/uniqpass-v16-passwords.txt
kitsec/lists/passwords/us-cities.txt
kitsec/lists/passwords/usernames.txt
kitsec-0.1.74.dist-info/METADATA
kitsec-0.1.74.dist-info/WHEEL
kitsec-0.1.74.dist-info/entry_points.txt
kitsec-0.1.74.dist-info/top_level.txt
kitsec-0.1.74.dist-info/RECORD
