Metadata-Version: 2.1
Name: kitsec
Version: 0.1.74
Summary: A package designed to streamline Ethical hackers workflows.
Home-page: https://github.com/kitsec-labs/kitsec-core
Author: Idriss CHEBAK
Author-email: idrisschebak@me.com
License: UNKNOWN
Platform: UNKNOWN
Classifier: Development Status :: 3 - Alpha
Classifier: Programming Language :: Python :: 3
Classifier: Programming Language :: Python :: 3.6
Classifier: Programming Language :: Python :: 3.7
Classifier: Programming Language :: Python :: 3.8
Classifier: Programming Language :: Python :: 3.9
Classifier: Programming Language :: Python :: 3.10
Requires-Dist: Pillow
Requires-Dist: wheel
Requires-Dist: setuptools (==60.5.0)
Requires-Dist: sleekxmpp (==1.3.1)
Requires-Dist: python-wappalyzer (==0.3.1)
Requires-Dist: beautifulsoup4 (==4.11.2)
Requires-Dist: python-magic (==0.4.27)
Requires-Dist: cve-search (==1.0.11)
Requires-Dist: wappalyzer (==1.0.0)
Requires-Dist: ipaddress (==1.0.7)
Requires-Dist: termcolor (==2.2.0)
Requires-Dist: requests (==2.28.1)
Requires-Dist: paramiko (==3.0.0)
Requires-Dist: tabulate (==0.9.0)
Requires-Dist: ipwhois (==1.2.0)
Requires-Dist: pandas (==1.2.5)
Requires-Dist: click (==7.1.2)
Requires-Dist: tqdm (==4.64.1)
Requires-Dist: nmap (==0.0.1)
Requires-Dist: bs4 (==0.0.1)
